setup.py
oaxmlapi/__init__.py
oaxmlapi/commands.py
oaxmlapi/connections.py
oaxmlapi/datatypes.py
oaxmlapi/utilities.py
oaxmlapi.egg-info/PKG-INFO
oaxmlapi.egg-info/SOURCES.txt
oaxmlapi.egg-info/dependency_links.txt
oaxmlapi.egg-info/not-zip-safe
oaxmlapi.egg-info/requires.txt
oaxmlapi.egg-info/top_level.txt