Metadata-Version: 1.0
Name: oaxmlapi
Version: 1.2
Summary: A Python wrapper around the NetSuite OpenAir XML API.
Home-page: https://github.com/goincremental/oaxmlapi
Author: Ryan Morrissey/Ben Hughes
Author-email: contactme@ryancmorrissey.com/bwghughes@gmail.com
License: LICENSE
Platform: UNKNOWN
